itensors/__init__.py
itensors/struct.py
itensors-0.1.3.dist-info/METADATA
itensors-0.1.3.dist-info/WHEEL
itensors-0.1.3.dist-info/RECORD
