Metadata-Version: 2.1
Name: itensors
Version: 0.1.3
Summary: Python port of the ITensors framework
Author: Miguel Costa
Author-email: miguelptcosta1995@gmail.com
Requires-Python: >=3.12,<4.0
Classifier: Programming Language :: Python :: 3
Classifier: Programming Language :: Python :: 3.12
Requires-Dist: ncon (>=2.0.0,<3.0.0)
Requires-Dist: numpy (>=2.3.1,<3.0.0)
